<?xml version="1.0" encoding="utf-8" ?>
<bcaster>
    <item item_url="data/afficheimg/20150227hhcerr.jpg" link="http://" text="" sort="0" position="right" price="" title="" />
    <item item_url="data/afficheimg/20150227ccpmjg.jpg" link="http://" text="额外服务俄方" sort="0" position="main" price="53453" title="" />
    <item item_url="data/afficheimg/20150227smmeee.jpg" link="http://" text="erfer" sort="0" position="main" price="$53/lb" title="" />
    <item item_url="data/afficheimg/20150227jqzocv.jpg" link="http://" text="grace" sort="0" position="main" price="$56/lb" title="" />
    <item item_url="data/afficheimg/20150227fqkkoc.jpg" link="http://" text="efsd" sort="0" position="main" price="$53/lb" title="" />
    <item item_url="data/afficheimg/20150227ypmyuh.jpg" link="http://" text="fsdfsdvs" sort="0" position="main" price="$56/lb" title="" />
    <item item_url="data/afficheimg/20150227lffnuo.jpg" link="http://" text="读书方法" sort="0" position="main" price="555" title="" />
    <item item_url="data/afficheimg/20150227wrgmgw.jpg" link="http://" text="就" sort="0" position="main" price="656" title="" />
    <item item_url="data/afficheimg/20150227ewonhq.jpg" link="http://" text="风" sort="0" position="main" price="434" title="" />
    <item item_url="data/afficheimg/20150227gliqvd.jpg" link="http://" text="东方大厦" sort="0" position="main" price="33" title="" />
    <item item_url="data/afficheimg/20150227khdppb.jpg" link="http://" text="dssd" sort="0" position="main" price="$53/lb" title="" />
    <item item_url="data/afficheimg/20150227xabrxc.jpg" link="http://" text="" sort="0" position="top" price="" title="" />
    <item item_url="data/afficheimg/20150227iiqhrz.jpg" link="http://" text="ergfd" sort="0" position="main" price="$53/lb" title="" />
    <item item_url="data/afficheimg/20150227fwmyuc.jpg" link="http://" text="dsadf" sort="0" position="main" price="$56/lb" title="" />
    <item item_url="data/afficheimg/20150227dqzyly.jpg" link="http://" text="fruit" sort="0" position="main" price="$53/lb" title="" />
    <item item_url="data/afficheimg/20150227pcjyrw.jpg" link="http://" text="wesas" sort="0" position="main" price="$53/lb" title="" />
    <item item_url="data/afficheimg/20150227wgyfua.jpg" link="http://" text="上的" sort="0" position="main" price="554" title="" />
    <item item_url="data/afficheimg/20150227rroeti.jpg" link="http://" text="" sort="0" position="left" price="" title="" />
    <item item_url="data/afficheimg/20150227qvzqrv.jpg" link="http://" text="发发" sort="0" position="main" price="33223" title="" />
    <item item_url="data/afficheimg/20150227oohgkd.jpg" link="http://" text="gdfser" sort="0" position="main" price="$53/lb" title="" />
    <item item_url="data/afficheimg/20150227kmhjbq.jpg" link="http://" text="娃娃" sort="0" position="main" price="654" title="" />
    <item item_url="data/afficheimg/20150227zuugnk.jpg" link="http://" text="犹太人人" sort="0" position="main" price="6" title="" />
    <item item_url="data/afficheimg/20150227mqqoqu.jpg" link="http://" text="发发和" sort="0" position="main" price="322" title="" />
</bcaster>